mouselungseg/__init__.py
mouselungseg/_version.py
mouselungseg/cli.py
mouselungseg/napari.yaml
mouselungseg/postprocess.py
mouselungseg/predict.py
mouselungseg/napari_plugin/__init__.py
mouselungseg/napari_plugin/_roi_widget.py
mouselungseg/napari_plugin/_widget.py
mouselungseg-0.0.8.dist-info/LICENSE
mouselungseg-0.0.8.dist-info/METADATA
mouselungseg-0.0.8.dist-info/WHEEL
mouselungseg-0.0.8.dist-info/entry_points.txt
mouselungseg-0.0.8.dist-info/top_level.txt
mouselungseg-0.0.8.dist-info/RECORD
