Metadata-Version: 2.1
Name: mouselungseg
Version: 0.0.8
Summary: YoloV8 model for the segmentation of the lungs in mice CT scans.
Author-email: Mallory Wittwer <mallory.wittwer@epfl.ch>
License: BSD 3-Clause License
Project-URL: homepage, https://github.com/EPFL-Center-for-Imaging/mouselungseg
Project-URL: repository, https://github.com/EPFL-Center-for-Imaging/mouselungseg
Classifier: Development Status :: 2 - Pre-Alpha
Classifier: License :: OSI Approved :: BSD License
Classifier: Programming Language :: Python :: 3
Classifier: Programming Language :: Python :: 3.9
Classifier: Programming Language :: Python :: 3.10
Classifier: Topic :: Scientific/Engineering :: Image Processing
Requires-Python: >=3.9
License-File: LICENSE
Requires-Dist: napari[all]>=0.4.16
Requires-Dist: qtpy
Requires-Dist: magicgui
Requires-Dist: numpy
Requires-Dist: pandas
Requires-Dist: tifffile
Requires-Dist: pooch==1.8.0
Requires-Dist: scikit-image
Requires-Dist: ultralytics
Requires-Dist: opencv-contrib-python-headless
